{
  "Total" : {
    "transaction" : "Total",
    "sampleCount" : 40,
    "errorCount" : 0,
    "errorPct" : 0.0,
    "meanResTime" : 0.4749999999999999,
    "medianResTime" : 0.0,
    "minResTime" : 0.0,
    "maxResTime" : 1.0,
    "pct1ResTime" : 1.0,
    "pct2ResTime" : 1.0,
    "pct3ResTime" : 1.0,
    "throughput" : 4.214519018017069,
    "receivedKBytesPerSec" : 7.385594741070488,
    "sentKBytesPerSec" : 0.0
  },
  "HTTP Request" : {
    "transaction" : "HTTP Request",
    "sampleCount" : 20,
    "errorCount" : 0,
    "errorPct" : 0.0,
    "meanResTime" : 0.7999999999999999,
    "medianResTime" : 1.0,
    "minResTime" : 0.0,
    "maxResTime" : 1.0,
    "pct1ResTime" : 1.0,
    "pct2ResTime" : 1.0,
    "pct3ResTime" : 1.0,
    "throughput" : 2.107481559536354,
    "receivedKBytesPerSec" : 6.884302555321391,
    "sentKBytesPerSec" : 0.0
  },
  "Debug" : {
    "transaction" : "Debug",
    "sampleCount" : 20,
    "errorCount" : 0,
    "errorPct" : 0.0,
    "meanResTime" : 0.15000000000000005,
    "medianResTime" : 0.0,
    "minResTime" : 0.0,
    "maxResTime" : 1.0,
    "pct1ResTime" : 1.0,
    "pct2ResTime" : 1.0,
    "pct3ResTime" : 1.0,
    "throughput" : 2.109259649862898,
    "receivedKBytesPerSec" : 0.5024940347500527,
    "sentKBytesPerSec" : 0.0
  }
}